{
  "https://feeds.bbci.co.uk/sport/rss.xml": {
    "etag": null,
    "lastModified": null,
    "lastRun": 1757316712012
  },
  "https://tools.cdc.gov/api/v2/resources/media/403372.rss": {
    "etag": null,
    "lastModified": null,
    "lastRun": 1757310292968
  },
  "https://www.hollywoodreporter.com/feed/": {
    "etag": "W/\"c64b34be49dc68e88bbd6e9ea6450e29\"",
    "lastModified": "Mon, 08 Sep 2025 05:22:24 GMT",
    "lastRun": 1757310295456
  },
  "https://www.cnbc.com/id/100003114/device/rss/rss.html": {
    "etag": null,
    "lastModified": null,
    "lastRun": 1757310293468
  },
  "https://feeds.footballco.com/kooora/feed/6p5bsxot7te8yick": {
    "etag": null,
    "lastModified": null,
    "lastRun": 1757316713441
  },
  "https://www.investing.com/rss/news.rss": {
    "etag": "W/\"112d-63e4394bfe839\"",
    "lastModified": "Mon, 08 Sep 2025 05:37:19 GMT",
    "lastRun": 1757310293760
  },
  "https://oilprice.com/rss/main": {
    "etag": null,
    "lastModified": null,
    "lastRun": 1757310293690
  },
  "https://www.ft.com/markets?format=rss": {
    "etag": "W/\"2c42-XJoxMx2bsKvpcJ7S4BsOcPDCPCs\"",
    "lastModified": null,
    "lastRun": 1757310293958
  },
  "https://www.pcgamer.com/rss/": {
    "etag": null,
    "lastModified": null,
    "lastRun": 1757310293955
  },
  "https://techcrunch.com/feed/": {
    "etag": "W/\"f1c863d13de326477fa2f1c14bbed97e\"",
    "lastModified": "Mon, 08 Sep 2025 03:59:18 GMT",
    "lastRun": 1757307469018
  },
  "https://www.engadget.com/rss.xml": {
    "etag": null,
    "lastModified": null,
    "lastRun": 1757310759144
  },
  "https://9to5mac.com/feed/": {
    "etag": "W/\"5213cf9ea5948fd7a58e7b5c25403ea9\"",
    "lastModified": "Mon, 08 Sep 2025 05:02:03 GMT",
    "lastRun": 1757310759791
  },
  "https://news.ycombinator.com/rss": {
    "etag": null,
    "lastModified": null,
    "lastRun": 1757310759993
  },
  "https://arstechnica.com/feed/": {
    "etag": "\"b521e48ccbf2881014a2a7cb08d0a76f\"",
    "lastModified": "Sun, 07 Sep 2025 13:00:58 GMT",
    "lastRun": 1757310759874
  },
  "https://www.newscientist.com/feed/home": {
    "etag": null,
    "lastModified": null,
    "lastRun": 1757310759826
  },
  "https://www.skynewsarabia.com/rss/business.xml": {
    "etag": null,
    "lastModified": "Mon, 08 Sep 2025 05:52:39 GMT",
    "lastRun": 1757310759743
  },
  "https://sports.almasryalyoum.com/feed/": {
    "etag": "\"083e5fd102eea07f828b8c039bebb227\"",
    "lastModified": "Mon, 08 Sep 2025 05:40:00 GMT",
    "lastRun": 1757310760018
  },
  "https://www.who.int/rss-feeds/news-english.xml": {
    "etag": null,
    "lastModified": "Sun, 07 Sep 2025 20:18:33 GMT",
    "lastRun": 1757277063701
  },
  "https://www.eater.com/rss/index.xml": {
    "etag": "W/\"28e12c401cfd2e633091818b2dba1f51\"",
    "lastModified": null,
    "lastRun": 1757137317043
  },
  "https://www.billboard.com/feed/": {
    "etag": "W/\"84c68cf04b86583d66d82f73a03c265f\"",
    "lastModified": "Mon, 08 Sep 2025 05:47:06 GMT",
    "lastRun": 1757316712492
  },
  "https://9to5google.com/feed/": {
    "etag": "W/\"78a615d9464bc1050a321c2f77a2c32e\"",
    "lastModified": "Mon, 08 Sep 2025 00:45:33 GMT",
    "lastRun": 1757316712531
  },
  "https://www.nasa.gov/rss/dyn/breaking_news.rss": {
    "etag": "W/\"7e9e4d9c1bfaa91a79f44704e81b33e2\"",
    "lastModified": "Mon, 08 Sep 2025 03:53:53 GMT",
    "lastRun": 1757316712576
  },
  "https://www.androidauthority.com/feed/": {
    "etag": "W/\"49536a629b074c4b3e4ceca217f4d70a-gzip\"",
    "lastModified": "Mon, 08 Sep 2025 07:30:04 GMT",
    "lastRun": 1757316712635
  },
  "https://www.masrawy.com/rss/feed/27/%D8%B1%D9%8A%D8%A7%D8%B6%D8%A9": {
    "etag": null,
    "lastModified": null,
    "lastRun": 1757316713208
  },
  "https://www.skynewsarabia.com/rss/technology.xml": {
    "etag": null,
    "lastModified": "Mon, 08 Sep 2025 07:30:01 GMT",
    "lastRun": 1757316712404
  },
  "https://aitnews.com/feed/": {
    "etag": null,
    "lastModified": "Sun, 07 Sep 2025 22:36:52 GMT",
    "lastRun": 1757284895709
  },
  "https://www.theverge.com/rss/index.xml": {
    "etag": "W/\"0abf32409df03fac26ebc1b311a4378b\"",
    "lastModified": null,
    "lastRun": 1757314821350
  },
  "https://www.tomshardware.com/feeds/all": {
    "etag": null,
    "lastModified": null,
    "lastRun": 1757314821913
  },
  "https://www.yallakora.com/feed/rssfeed": {
    "etag": null,
    "lastModified": null,
    "lastRun": 1757314823108
  },
  "https://www.gsmarena.com/rss-news-reviews.php3": {
    "etag": null,
    "lastModified": null,
    "lastRun": 1757314822664
  },
  "https://variety.com/feed/": {
    "etag": "W/\"f142241c46d616e09dbeb1597e169c39\"",
    "lastModified": "Mon, 08 Sep 2025 06:03:48 GMT",
    "lastRun": 1757314823538
  },
  "https://www.nature.com/nature.rss": {
    "etag": "\"06a4e30e52ef2e9e49483b57a897f429\"",
    "lastModified": null,
    "lastRun": 1757098718468
  },
  "https://www.skynewsarabia.com/rss/varieties.xml": {
    "etag": null,
    "lastModified": "Mon, 08 Sep 2025 06:53:08 GMT",
    "lastRun": 1757314389130
  },
  "https://www.bbc.com/culture/feed.rss": {
    "etag": null,
    "lastModified": null,
    "lastRun": 1757314389346
  },
  "https://www.delish.com/rss/all.xml/": {
    "etag": null,
    "lastModified": null,
    "lastRun": 1757314389502
  },
  "https://www.wired.com/feed/rss": {
    "etag": null,
    "lastModified": null,
    "lastRun": 1757314389678
  },
  "https://www.technologyreview.com/feed/": {
    "etag": "W/\"65cfd6bc0c326a659abcdc6cd2709011\"",
    "lastModified": "Fri, 05 Sep 2025 20:38:20 GMT",
    "lastRun": 1757116093644
  },
  "https://www.livescience.com/feeds/all": {
    "etag": null,
    "lastModified": null,
    "lastRun": 1757314389745
  },
  "https://www.assabah.ma/feed/": {
    "etag": "W/\"ba6bb16e64edf803884edb2f51b270a1\"",
    "lastModified": "Mon, 08 Sep 2025 05:18:00 GMT",
    "lastRun": 1757314394503
  },
  "https://attounisiyoun.com/feed/": {
    "etag": "\"4cb7285195a887c35c4b4079be3fc256-gzip\"",
    "lastModified": "Mon, 30 Jun 2025 19:37:38 GMT",
    "lastRun": 1757310761702
  }
}