{
  "https://feeds.bbci.co.uk/sport/rss.xml": {
    "etag": null,
    "lastModified": null,
    "lastRun": 1759348870740
  },
  "https://tools.cdc.gov/api/v2/resources/media/403372.rss": {
    "etag": null,
    "lastModified": null,
    "lastRun": 1759346972448
  },
  "https://www.hollywoodreporter.com/feed/": {
    "etag": "W/\"dfe0d35118a81a26e4034f8c69d81c6b\"",
    "lastModified": "Wed, 01 Oct 2025 19:28:16 GMT",
    "lastRun": 1759346972596
  },
  "https://www.cnbc.com/id/100003114/device/rss/rss.html": {
    "etag": null,
    "lastModified": null,
    "lastRun": 1759346972539
  },
  "https://feeds.footballco.com/kooora/feed/6p5bsxot7te8yick": {
    "etag": null,
    "lastModified": null,
    "lastRun": 1759348871545
  },
  "https://www.investing.com/rss/news.rss": {
    "etag": "W/\"1050-6401dbe00c1f3\"",
    "lastModified": "Wed, 01 Oct 2025 19:19:06 GMT",
    "lastRun": 1759346972807
  },
  "https://oilprice.com/rss/main": {
    "etag": null,
    "lastModified": null,
    "lastRun": 1759346973241
  },
  "https://www.ft.com/markets?format=rss": {
    "etag": "W/\"2c62-XybQHn4S7k7g8x/usxd+cVvVsNI\"",
    "lastModified": null,
    "lastRun": 1759346973162
  },
  "https://www.pcgamer.com/rss/": {
    "etag": null,
    "lastModified": null,
    "lastRun": 1759346973104
  },
  "https://techcrunch.com/feed/": {
    "etag": "W/\"5a9489637e5ec4dcbc494a05b08f24d7\"",
    "lastModified": "Wed, 01 Oct 2025 19:17:12 GMT",
    "lastRun": 1759346531935
  },
  "https://www.engadget.com/rss.xml": {
    "etag": null,
    "lastModified": null,
    "lastRun": 1759346532261
  },
  "https://9to5mac.com/feed/": {
    "etag": "W/\"df8bda58f3a0492a8352729b78ffd6ab\"",
    "lastModified": "Wed, 01 Oct 2025 18:17:08 GMT",
    "lastRun": 1759345666256
  },
  "https://news.ycombinator.com/rss": {
    "etag": null,
    "lastModified": null,
    "lastRun": 1759346532329
  },
  "https://arstechnica.com/feed/": {
    "etag": "\"abf47a3bdaf85ae3ff1d8180a811695e\"",
    "lastModified": "Wed, 01 Oct 2025 19:04:03 GMT",
    "lastRun": 1759346532669
  },
  "https://www.newscientist.com/feed/home": {
    "etag": null,
    "lastModified": null,
    "lastRun": 1759346532423
  },
  "https://www.skynewsarabia.com/rss/business.xml": {
    "etag": null,
    "lastModified": null,
    "lastRun": 1759346532601
  },
  "https://sports.almasryalyoum.com/feed/": {
    "etag": "\"4fd0036d03d23c70e41373f8f7369a1a\"",
    "lastModified": "Wed, 01 Oct 2025 19:08:19 GMT",
    "lastRun": 1759346532811
  },
  "https://www.who.int/rss-feeds/news-english.xml": {
    "etag": null,
    "lastModified": "Wed, 01 Oct 2025 14:15:10 GMT",
    "lastRun": 1759337175935
  },
  "https://www.eater.com/rss/index.xml": {
    "etag": "W/\"c74eeb05c48f5934bbf3e8d163cfedc2\"",
    "lastModified": null,
    "lastRun": 1759348870718
  },
  "https://www.billboard.com/feed/": {
    "etag": "W/\"2bd31ad50bad43f84998dc93c5f0d886\"",
    "lastModified": "Wed, 01 Oct 2025 19:41:14 GMT",
    "lastRun": 1759348873166
  },
  "https://9to5google.com/feed/": {
    "etag": "W/\"716945f50bcbabdfc00f662a0e70b12b\"",
    "lastModified": "Wed, 01 Oct 2025 18:15:50 GMT",
    "lastRun": 1759348870893
  },
  "https://www.nasa.gov/rss/dyn/breaking_news.rss": {
    "etag": "W/\"7033a65e46eb31a8fcb412c99d83cc9e\"",
    "lastModified": "Wed, 01 Oct 2025 19:39:47 GMT",
    "lastRun": 1759348870935
  },
  "https://www.androidauthority.com/feed/": {
    "etag": "W/\"5bf60398bef9b4a74393355ad322dbb0-gzip\"",
    "lastModified": "Wed, 01 Oct 2025 19:16:21 GMT",
    "lastRun": 1759348871066
  },
  "https://www.masrawy.com/rss/feed/27/%D8%B1%D9%8A%D8%A7%D8%B6%D8%A9": {
    "etag": null,
    "lastModified": null,
    "lastRun": 1759348871834
  },
  "https://www.skynewsarabia.com/rss/technology.xml": {
    "etag": null,
    "lastModified": null,
    "lastRun": 1759348871103
  },
  "https://aitnews.com/feed/": {
    "etag": null,
    "lastModified": "Wed, 01 Oct 2025 19:32:44 GMT",
    "lastRun": 1759348871696
  },
  "https://www.theverge.com/rss/index.xml": {
    "etag": "W/\"8f1f8d765ede9d2fa95c3db1de73bd37\"",
    "lastModified": null,
    "lastRun": 1759347933631
  },
  "https://www.tomshardware.com/feeds/all": {
    "etag": null,
    "lastModified": null,
    "lastRun": 1759347934657
  },
  "https://www.yallakora.com/feed/rssfeed": {
    "etag": null,
    "lastModified": null,
    "lastRun": 1759347934733
  },
  "https://www.gsmarena.com/rss-news-reviews.php3": {
    "etag": null,
    "lastModified": null,
    "lastRun": 1759347935073
  },
  "https://variety.com/feed/": {
    "etag": "W/\"a00b0187a23d6c6f13a6f4aa253edfc2\"",
    "lastModified": "Wed, 01 Oct 2025 19:38:31 GMT",
    "lastRun": 1759347934022
  },
  "https://www.nature.com/nature.rss": {
    "etag": "\"c1feff54981bcc373f254959d48cbb66\"",
    "lastModified": null,
    "lastRun": 1759340905106
  },
  "https://www.skynewsarabia.com/rss/varieties.xml": {
    "etag": null,
    "lastModified": null,
    "lastRun": 1759348387831
  },
  "https://www.bbc.com/culture/feed.rss": {
    "etag": null,
    "lastModified": null,
    "lastRun": 1759348387974
  },
  "https://www.delish.com/rss/all.xml/": {
    "etag": null,
    "lastModified": null,
    "lastRun": 1759348388249
  },
  "https://www.wired.com/feed/rss": {
    "etag": null,
    "lastModified": null,
    "lastRun": 1759348388294
  },
  "https://www.technologyreview.com/feed/": {
    "etag": "W/\"36afa214749ecf2799699149dea0efa4\"",
    "lastModified": "Wed, 01 Oct 2025 18:38:23 GMT",
    "lastRun": 1759344834958
  },
  "https://www.livescience.com/feeds/all": {
    "etag": null,
    "lastModified": null,
    "lastRun": 1759348388378
  },
  "https://www.assabah.ma/feed/": {
    "etag": "W/\"373190f9ac3dc874be89f3b9b8008572\"",
    "lastModified": "Wed, 01 Oct 2025 18:53:13 GMT",
    "lastRun": 1759348394178
  },
  "https://attounisiyoun.com/feed/": {
    "etag": "\"24a211e7f2175142b804b3c6bd3c4ae9-gzip\"",
    "lastModified": "Tue, 30 Sep 2025 16:29:03 GMT",
    "lastRun": 1759346532985
  }
}