{
  "https://feeds.bbci.co.uk/sport/rss.xml": {
    "etag": null,
    "lastModified": null,
    "lastRun": 1775249449281
  },
  "https://tools.cdc.gov/api/v2/resources/media/403372.rss": {
    "etag": null,
    "lastModified": null,
    "lastRun": 1775245453955
  },
  "https://www.hollywoodreporter.com/feed/": {
    "etag": "W/\"bd0d246a1faca91facf00c25efcd6edb\"",
    "lastModified": "Fri, 03 Apr 2026 19:41:10 GMT",
    "lastRun": 1775245456662
  },
  "https://www.cnbc.com/id/100003114/device/rss/rss.html": {
    "etag": null,
    "lastModified": null,
    "lastRun": 1775245454313
  },
  "https://feeds.footballco.com/kooora/feed/6p5bsxot7te8yick": {
    "etag": null,
    "lastModified": null,
    "lastRun": 1775249450022
  },
  "https://www.investing.com/rss/news.rss": {
    "etag": "W/\"1064-64e93744b46eb\"",
    "lastModified": "Fri, 03 Apr 2026 19:37:58 GMT",
    "lastRun": 1775245454692
  },
  "https://oilprice.com/rss/main": {
    "etag": null,
    "lastModified": null,
    "lastRun": 1775245455235
  },
  "https://www.ft.com/markets?format=rss": {
    "etag": "W/\"2e0a-U4S1oakgPPysHiCAAPfY8UANH90\"",
    "lastModified": null,
    "lastRun": 1775245454713
  },
  "https://www.pcgamer.com/rss/": {
    "etag": null,
    "lastModified": null,
    "lastRun": 1775245455194
  },
  "https://techcrunch.com/feed/": {
    "etag": "W/\"b0de1aa77603104178b44a39a2beb502\"",
    "lastModified": "Fri, 03 Apr 2026 19:02:22 GMT",
    "lastRun": 1775242962880
  },
  "https://www.engadget.com/rss.xml": {
    "etag": null,
    "lastModified": null,
    "lastRun": 1775242962777
  },
  "https://9to5mac.com/feed/": {
    "etag": "W/\"e664dba1fa13d18c703a1ce16f33f1a5\"",
    "lastModified": "Fri, 03 Apr 2026 19:02:14 GMT",
    "lastRun": 1775242964604
  },
  "https://news.ycombinator.com/rss": {
    "etag": null,
    "lastModified": null,
    "lastRun": 1775242963352
  },
  "https://arstechnica.com/feed/": {
    "etag": "\"a1a564c65322027ae8b81979714c2e4c\"",
    "lastModified": "Fri, 03 Apr 2026 17:53:00 GMT",
    "lastRun": 1775242963212
  },
  "https://www.newscientist.com/feed/home": {
    "etag": null,
    "lastModified": null,
    "lastRun": 1775242963382
  },
  "https://www.skynewsarabia.com/rss/business.xml": {
    "etag": null,
    "lastModified": "Fri, 03 Apr 2026 19:02:01 GMT",
    "lastRun": 1775242963093
  },
  "https://sports.almasryalyoum.com/feed/": {
    "etag": "\"74905a3f6854f4388323b43ae440b62b\"",
    "lastModified": "Fri, 03 Apr 2026 18:40:16 GMT",
    "lastRun": 1775242963489
  },
  "https://www.who.int/rss-feeds/news-english.xml": {
    "etag": null,
    "lastModified": "Fri, 03 Apr 2026 09:10:11 GMT",
    "lastRun": 1775231469807
  },
  "https://www.eater.com/rss/index.xml": {
    "etag": "W/\"a6d221fc660ab549a1c2931bf3a838ea\"",
    "lastModified": null,
    "lastRun": 1775239584545
  },
  "https://www.billboard.com/feed/": {
    "etag": "W/\"4d54b41b5ff2268038128a1029e85bb9\"",
    "lastModified": "Fri, 03 Apr 2026 18:05:32 GMT",
    "lastRun": 1775239587055
  },
  "https://9to5google.com/feed/": {
    "etag": "W/\"9a7b550f7f65c91e65f7ba888e5e518d\"",
    "lastModified": "Fri, 03 Apr 2026 17:24:43 GMT",
    "lastRun": 1775239584789
  },
  "https://www.nasa.gov/rss/dyn/breaking_news.rss": {
    "etag": "W/\"42a8c870a956faabd259541fb8aa7ae3\"",
    "lastModified": "Fri, 03 Apr 2026 17:46:44 GMT",
    "lastRun": 1775239584797
  },
  "https://www.androidauthority.com/feed/": {
    "etag": "W/\"0a0f038dd00aa1b7aa30fc647ec45e3a-gzip\"",
    "lastModified": "Fri, 03 Apr 2026 17:24:11 GMT",
    "lastRun": 1775239584876
  },
  "https://www.masrawy.com/rss/feed/27/%D8%B1%D9%8A%D8%A7%D8%B6%D8%A9": {
    "etag": null,
    "lastModified": "Fri, 03 Apr 2026 17:59:51 GMT",
    "lastRun": 1775239584588
  },
  "https://www.skynewsarabia.com/rss/technology.xml": {
    "etag": null,
    "lastModified": "Fri, 03 Apr 2026 18:05:15 GMT",
    "lastRun": 1775239584414
  },
  "https://aitnews.com/feed/": {
    "etag": null,
    "lastModified": "Fri, 03 Apr 2026 13:45:46 GMT",
    "lastRun": 1775231471261
  },
  "https://www.theverge.com/rss/index.xml": {
    "etag": "W/\"c314a0704b18ab06c8fa63b457472a3d\"",
    "lastModified": null,
    "lastRun": 1775249449030
  },
  "https://www.tomshardware.com/feeds/all": {
    "etag": null,
    "lastModified": null,
    "lastRun": 1775249450804
  },
  "https://www.yallakora.com/feed/rssfeed": {
    "etag": null,
    "lastModified": null,
    "lastRun": 1775249449716
  },
  "https://www.gsmarena.com/rss-news-reviews.php3": {
    "etag": null,
    "lastModified": null,
    "lastRun": 1775249451113
  },
  "https://variety.com/feed/": {
    "etag": "W/\"b5cd3d6544d559ea2d8b5f58e08e42f9\"",
    "lastModified": "Fri, 03 Apr 2026 20:40:46 GMT",
    "lastRun": 1775249449376
  },
  "https://www.nature.com/nature.rss": {
    "etag": "\"ac3ac0ded689e3cbca82ef68ce6d9b3f\"",
    "lastModified": null,
    "lastRun": 1775171889186
  },
  "https://www.skynewsarabia.com/rss/varieties.xml": {
    "etag": null,
    "lastModified": "Fri, 03 Apr 2026 13:42:07 GMT",
    "lastRun": 1775223780451
  },
  "https://www.bbc.com/culture/feed.rss": {
    "etag": null,
    "lastModified": null,
    "lastRun": 1775223780676
  },
  "https://www.delish.com/rss/all.xml/": {
    "etag": null,
    "lastModified": null,
    "lastRun": 1775223780908
  },
  "https://www.wired.com/feed/rss": {
    "etag": null,
    "lastModified": null,
    "lastRun": 1775223780904
  },
  "https://www.technologyreview.com/feed/": {
    "etag": "W/\"18f3f7780f80b393f5b5f8e8167b90f9\"",
    "lastModified": "Fri, 03 Apr 2026 13:11:30 GMT",
    "lastRun": 1775223780873
  },
  "https://www.livescience.com/feeds/all": {
    "etag": null,
    "lastModified": null,
    "lastRun": 1775223781041
  },
  "https://www.assabah.ma/feed/": {
    "etag": "W/\"c283749d989860561e58d59c638f2435\"",
    "lastModified": "Fri, 03 Apr 2026 13:26:12 GMT",
    "lastRun": 1775223786658
  },
  "https://attounisiyoun.com/feed/": {
    "etag": "\"d674b508ca8e15ec3b61170475d8a19a-gzip\"",
    "lastModified": "Wed, 01 Apr 2026 17:39:49 GMT",
    "lastRun": 1775242963872
  }
}