{
  "https://feeds.bbci.co.uk/sport/rss.xml": {
    "etag": null,
    "lastModified": null,
    "lastRun": 1772570829887
  },
  "https://tools.cdc.gov/api/v2/resources/media/403372.rss": {
    "etag": null,
    "lastModified": null,
    "lastRun": 1772490895220
  },
  "https://www.hollywoodreporter.com/feed/": {
    "etag": "W/\"afae5bdf1ed32d2f41fae5af9e96112e\"",
    "lastModified": "Mon, 02 Mar 2026 22:32:58 GMT",
    "lastRun": 1772490897215
  },
  "https://www.cnbc.com/id/100003114/device/rss/rss.html": {
    "etag": null,
    "lastModified": null,
    "lastRun": 1772490895352
  },
  "https://feeds.footballco.com/kooora/feed/6p5bsxot7te8yick": {
    "etag": null,
    "lastModified": null,
    "lastRun": 1772570830170
  },
  "https://www.investing.com/rss/news.rss": {
    "etag": "W/\"1027-64c11eea00ca4\"",
    "lastModified": "Mon, 02 Mar 2026 22:16:01 GMT",
    "lastRun": 1772490895458
  },
  "https://oilprice.com/rss/main": {
    "etag": null,
    "lastModified": null,
    "lastRun": 1772490895431
  },
  "https://www.ft.com/markets?format=rss": {
    "etag": "W/\"2c16-5lVKUVr1jILGTuVUW8mZJ7959PQ\"",
    "lastModified": null,
    "lastRun": 1772490895849
  },
  "https://www.pcgamer.com/rss/": {
    "etag": null,
    "lastModified": null,
    "lastRun": 1772490895711
  },
  "https://techcrunch.com/feed/": {
    "etag": "W/\"81ae9bade419fa1ac510caaec3191e77\"",
    "lastModified": "Tue, 03 Mar 2026 20:46:20 GMT",
    "lastRun": 1772570829321
  },
  "https://www.engadget.com/rss.xml": {
    "etag": null,
    "lastModified": null,
    "lastRun": 1772570829724
  },
  "https://9to5mac.com/feed/": {
    "etag": "W/\"4d1e39a1715ffc160f688eae871ae0db\"",
    "lastModified": "Tue, 03 Mar 2026 20:27:39 GMT",
    "lastRun": 1772570830121
  },
  "https://news.ycombinator.com/rss": {
    "etag": null,
    "lastModified": null,
    "lastRun": 1772570830259
  },
  "https://arstechnica.com/feed/": {
    "etag": "\"67c5b2b3326c0af827f008f318154578\"",
    "lastModified": "Tue, 03 Mar 2026 20:33:31 GMT",
    "lastRun": 1772570830102
  },
  "https://www.newscientist.com/feed/home": {
    "etag": null,
    "lastModified": null,
    "lastRun": 1772570830419
  },
  "https://www.skynewsarabia.com/rss/business.xml": {
    "etag": null,
    "lastModified": "Tue, 03 Mar 2026 20:46:53 GMT",
    "lastRun": 1772570829818
  },
  "https://sports.almasryalyoum.com/feed/": {
    "etag": "\"e78be95d189bc961525a160f1fe0647e\"",
    "lastModified": "Tue, 03 Mar 2026 20:25:02 GMT",
    "lastRun": 1772570830433
  },
  "https://www.who.int/rss-feeds/news-english.xml": {
    "etag": null,
    "lastModified": "Tue, 03 Mar 2026 14:00:14 GMT",
    "lastRun": 1772567160307
  },
  "https://www.eater.com/rss/index.xml": {
    "etag": "W/\"70b7f2301f47cf2db0f2b211bdafb554\"",
    "lastModified": null,
    "lastRun": 1772567160412
  },
  "https://www.billboard.com/feed/": {
    "etag": "W/\"c4b93c85d828ea7da06670f2dead250c\"",
    "lastModified": "Tue, 03 Mar 2026 19:44:06 GMT",
    "lastRun": 1772567163133
  },
  "https://9to5google.com/feed/": {
    "etag": "W/\"a6e6d350de19a85f98038da0220fccd0\"",
    "lastModified": "Tue, 03 Mar 2026 19:45:52 GMT",
    "lastRun": 1772567161622
  },
  "https://www.nasa.gov/rss/dyn/breaking_news.rss": {
    "etag": "W/\"127e931924dc86ebc1127bff2d6f0fb2\"",
    "lastModified": "Tue, 03 Mar 2026 19:20:03 GMT",
    "lastRun": 1772567160581
  },
  "https://www.androidauthority.com/feed/": {
    "etag": "W/\"b06c5b68d614a893dfd9c94bdec67ccd-gzip\"",
    "lastModified": "Tue, 03 Mar 2026 19:37:54 GMT",
    "lastRun": 1772567160651
  },
  "https://www.masrawy.com/rss/feed/27/%D8%B1%D9%8A%D8%A7%D8%B6%D8%A9": {
    "etag": null,
    "lastModified": "Tue, 03 Mar 2026 19:46:01 GMT",
    "lastRun": 1772567161230
  },
  "https://www.skynewsarabia.com/rss/technology.xml": {
    "etag": null,
    "lastModified": null,
    "lastRun": 1772567160855
  },
  "https://aitnews.com/feed/": {
    "etag": null,
    "lastModified": "Tue, 03 Mar 2026 15:24:07 GMT",
    "lastRun": 1772567161652
  },
  "https://www.theverge.com/rss/index.xml": {
    "etag": "W/\"8c5c41cabe78cd9f0efffb8a8a7f47bd\"",
    "lastModified": null,
    "lastRun": 1772558715691
  },
  "https://www.tomshardware.com/feeds/all": {
    "etag": null,
    "lastModified": null,
    "lastRun": 1772558716549
  },
  "https://www.yallakora.com/feed/rssfeed": {
    "etag": null,
    "lastModified": null,
    "lastRun": 1772558716044
  },
  "https://www.gsmarena.com/rss-news-reviews.php3": {
    "etag": null,
    "lastModified": null,
    "lastRun": 1772558717058
  },
  "https://variety.com/feed/": {
    "etag": "W/\"3f556ab563f5f983a8d664fd52aee308\"",
    "lastModified": "Tue, 03 Mar 2026 17:17:37 GMT",
    "lastRun": 1772558715872
  },
  "https://www.nature.com/nature.rss": {
    "etag": "\"0f3bbfa3ce58b7c57a52ce0def7e7e8d\"",
    "lastModified": null,
    "lastRun": 1772568209880
  },
  "https://www.skynewsarabia.com/rss/varieties.xml": {
    "etag": null,
    "lastModified": null,
    "lastRun": 1772568209728
  },
  "https://www.bbc.com/culture/feed.rss": {
    "etag": null,
    "lastModified": null,
    "lastRun": 1772568209961
  },
  "https://www.delish.com/rss/all.xml/": {
    "etag": null,
    "lastModified": null,
    "lastRun": 1772568210196
  },
  "https://www.wired.com/feed/rss": {
    "etag": null,
    "lastModified": null,
    "lastRun": 1772568210209
  },
  "https://www.technologyreview.com/feed/": {
    "etag": "W/\"6e3e51d1556aea344d65f6f316bd483d\"",
    "lastModified": "Tue, 03 Mar 2026 18:24:19 GMT",
    "lastRun": 1772568210482
  },
  "https://www.livescience.com/feeds/all": {
    "etag": null,
    "lastModified": null,
    "lastRun": 1772568210290
  },
  "https://www.assabah.ma/feed/": {
    "etag": "W/\"0df288ec2ee3876e29688f285fb25a72\"",
    "lastModified": "Tue, 03 Mar 2026 20:00:26 GMT",
    "lastRun": 1772568214979
  },
  "https://attounisiyoun.com/feed/": {
    "etag": "\"0bf7e2859a63d27be7bc87cf6a861351-gzip\"",
    "lastModified": "Tue, 03 Mar 2026 16:12:17 GMT",
    "lastRun": 1772570830821
  }
}