{
  "https://feeds.bbci.co.uk/sport/rss.xml": {
    "etag": null,
    "lastModified": null,
    "lastRun": 1761504035754
  },
  "https://tools.cdc.gov/api/v2/resources/media/403372.rss": {
    "etag": null,
    "lastModified": null,
    "lastRun": 1761497986278
  },
  "https://www.hollywoodreporter.com/feed/": {
    "etag": "W/\"ec77b2f3b79c0b25045942a96c29ae42\"",
    "lastModified": "Sun, 26 Oct 2025 16:51:06 GMT",
    "lastRun": 1761497988350
  },
  "https://www.cnbc.com/id/100003114/device/rss/rss.html": {
    "etag": null,
    "lastModified": null,
    "lastRun": 1761497986671
  },
  "https://feeds.footballco.com/kooora/feed/6p5bsxot7te8yick": {
    "etag": null,
    "lastModified": null,
    "lastRun": 1761504036588
  },
  "https://www.investing.com/rss/news.rss": {
    "etag": "W/\"10a7-64212a26dc529\"",
    "lastModified": "Sun, 26 Oct 2025 16:54:22 GMT",
    "lastRun": 1761497986725
  },
  "https://oilprice.com/rss/main": {
    "etag": null,
    "lastModified": null,
    "lastRun": 1761497986837
  },
  "https://www.ft.com/markets?format=rss": {
    "etag": "W/\"2cd1-T8tKWzx9YMrHhajoNOgWl/KH+ss\"",
    "lastModified": null,
    "lastRun": 1761497987066
  },
  "https://www.pcgamer.com/rss/": {
    "etag": null,
    "lastModified": null,
    "lastRun": 1761497987058
  },
  "https://techcrunch.com/feed/": {
    "etag": "W/\"eed9852475e45dfe1414b8a0776ada3e\"",
    "lastModified": "Sun, 26 Oct 2025 17:29:57 GMT",
    "lastRun": 1761500858634
  },
  "https://www.engadget.com/rss.xml": {
    "etag": null,
    "lastModified": null,
    "lastRun": 1761500858795
  },
  "https://9to5mac.com/feed/": {
    "etag": "W/\"7837e8bd7f0f07b82a4a1239bbb98a3e\"",
    "lastModified": "Sun, 26 Oct 2025 17:25:47 GMT",
    "lastRun": 1761500859363
  },
  "https://news.ycombinator.com/rss": {
    "etag": null,
    "lastModified": null,
    "lastRun": 1761500859572
  },
  "https://arstechnica.com/feed/": {
    "etag": "\"9452d9b45cd86742fb2212d9d8abe5fd\"",
    "lastModified": "Sat, 25 Oct 2025 11:00:09 GMT",
    "lastRun": 1761500859317
  },
  "https://www.newscientist.com/feed/home": {
    "etag": null,
    "lastModified": null,
    "lastRun": 1761500859465
  },
  "https://www.skynewsarabia.com/rss/business.xml": {
    "etag": null,
    "lastModified": null,
    "lastRun": 1761500859086
  },
  "https://sports.almasryalyoum.com/feed/": {
    "etag": "\"701b6aaa9e70c7901d09f74405f4066d\"",
    "lastModified": "Sun, 26 Oct 2025 17:32:28 GMT",
    "lastRun": 1761500859604
  },
  "https://www.who.int/rss-feeds/news-english.xml": {
    "etag": null,
    "lastModified": "Sun, 26 Oct 2025 14:15:25 GMT",
    "lastRun": 1761488161741
  },
  "https://www.eater.com/rss/index.xml": {
    "etag": "W/\"c1fe67601ba47879d98022574e6376a0\"",
    "lastModified": null,
    "lastRun": 1761468387787
  },
  "https://www.billboard.com/feed/": {
    "etag": "W/\"225fb5d729923ff9de8179533d646964\"",
    "lastModified": "Sun, 26 Oct 2025 15:59:37 GMT",
    "lastRun": 1761494492907
  },
  "https://9to5google.com/feed/": {
    "etag": "W/\"e9bfe4b59a0effa7db82ba529f9cab96\"",
    "lastModified": "Fri, 24 Oct 2025 20:27:02 GMT",
    "lastRun": 1761494493132
  },
  "https://www.nasa.gov/rss/dyn/breaking_news.rss": {
    "etag": "W/\"4fde6a5817285a1549b5903dd6c7380b\"",
    "lastModified": "Fri, 24 Oct 2025 18:29:56 GMT",
    "lastRun": 1761332461459
  },
  "https://www.androidauthority.com/feed/": {
    "etag": "W/\"23aaf08537251bb9facf3b59e17ebdca-gzip\"",
    "lastModified": "Sun, 26 Oct 2025 12:00:06 GMT",
    "lastRun": 1761483389757
  },
  "https://www.masrawy.com/rss/feed/27/%D8%B1%D9%8A%D8%A7%D8%B6%D8%A9": {
    "etag": null,
    "lastModified": null,
    "lastRun": 1761494493263
  },
  "https://www.skynewsarabia.com/rss/technology.xml": {
    "etag": null,
    "lastModified": null,
    "lastRun": 1761494492928
  },
  "https://aitnews.com/feed/": {
    "etag": "\"ee35e43c7ee0bf2a81823c3318836efc\"",
    "lastModified": "Sat, 25 Oct 2025 21:48:46 GMT",
    "lastRun": 1761429408815
  },
  "https://www.theverge.com/rss/index.xml": {
    "etag": "W/\"f4caabb995414c5878c68192e1d7ba62\"",
    "lastModified": null,
    "lastRun": 1761499847598
  },
  "https://www.tomshardware.com/feeds/all": {
    "etag": null,
    "lastModified": null,
    "lastRun": 1761504036833
  },
  "https://www.yallakora.com/feed/rssfeed": {
    "etag": null,
    "lastModified": null,
    "lastRun": 1761504036684
  },
  "https://www.gsmarena.com/rss-news-reviews.php3": {
    "etag": null,
    "lastModified": null,
    "lastRun": 1761504037008
  },
  "https://variety.com/feed/": {
    "etag": "W/\"e2dad4b61df230156a77352275ef8bca\"",
    "lastModified": "Sun, 26 Oct 2025 18:10:18 GMT",
    "lastRun": 1761502533316
  },
  "https://www.nature.com/nature.rss": {
    "etag": "\"42873c6a6bf7f24d74eea39c72f0106e\"",
    "lastModified": null,
    "lastRun": 1761364416005
  },
  "https://www.skynewsarabia.com/rss/varieties.xml": {
    "etag": null,
    "lastModified": null,
    "lastRun": 1761494025033
  },
  "https://www.bbc.com/culture/feed.rss": {
    "etag": null,
    "lastModified": null,
    "lastRun": 1761494024929
  },
  "https://www.delish.com/rss/all.xml/": {
    "etag": null,
    "lastModified": null,
    "lastRun": 1761494025095
  },
  "https://www.wired.com/feed/rss": {
    "etag": null,
    "lastModified": null,
    "lastRun": 1761494025162
  },
  "https://www.technologyreview.com/feed/": {
    "etag": "W/\"33c7c05b17501f2878ac55d60477a948\"",
    "lastModified": "Fri, 24 Oct 2025 16:35:48 GMT",
    "lastRun": 1761326016397
  },
  "https://www.livescience.com/feeds/all": {
    "etag": null,
    "lastModified": null,
    "lastRun": 1761494025304
  },
  "https://www.assabah.ma/feed/": {
    "etag": "W/\"f74345d4c2aa2d0b3d28834fbd0b86fa\"",
    "lastModified": "Sun, 26 Oct 2025 15:52:59 GMT",
    "lastRun": 1761494030423
  },
  "https://attounisiyoun.com/feed/": {
    "etag": "\"b2929f76757772eeba19efeb1ac210bd-gzip\"",
    "lastModified": "Tue, 14 Oct 2025 12:22:08 GMT",
    "lastRun": 1761432440787
  }
}