[
  {
    "id": "c401bc5b2ef7ca43",
    "title": "المقاولون العرب يعلن رحيل محمد مكي وتعيين طلعت محرم مديرًا فنيًا",
    "link": "https://www.yallakora.com/egyptian-league/2977/news/525064/%d8%a7%d9%84%d9%85%d9%82%d8%a7%d9%88%d9%84%d9%88%d9%86-%d8%a7%d9%84%d8%b9%d8%b1%d8%a8-%d9%8a%d8%b9%d9%84%d9%86-%d8%b1%d8%ad%d9%8a%d9%84-%d9%85%d8%ad%d9%85%d8%af-%d9%85%d9%83%d9%8a-%d9%88%d8%aa%d8%b9%d9%8a%d9%8a%d9%86-%d8%b7%d9%84%d8%b9%d8%aa-%d9%85%d8%ad%d8%b1%d9%85-%d9%85%d8%af%d9%8a%d8%b1-%d8%a7-%d9%81%d9%86%d9%8a-%d8%a7",
    "summary": "تقدم مجلس إدارة نادي المقاولون العرب، برئاسة محسن صلاح، بخالص الشكر والتقدير لمحمد مكي، المدير الفني للفريق، على جهوده وعطائه الكبير طوال فترة توليه المسؤولية الفنية.",
    "body": null,
    "image": null,
    "pubDate": "2025-09-28T20:40:00.000Z",
    "source": {
      "name": "Yallakora",
      "homepage": "https://www.yallakora.com/feed/rssfeed"
    },
    "lang": "en",
    "category": "entertainment",
    "region": "global"
  },
  {
    "id": "c12b162c739de972",
    "title": "\"أكره الخسارة\".. توماسبيرج يتحدث عن.. شخصيته والاستفادة من المنافسين وإدارة اللاعبين",
    "link": "https://www.yallakora.com/egyptian-league/2977/news/524985/-%d8%a3%d9%83%d8%b1%d9%87-%d8%a7%d9%84%d8%ae%d8%b3%d8%a7%d8%b1%d8%a9-%d8%aa%d9%88%d9%85%d8%a7%d8%b3%d8%a8%d9%8a%d8%b1%d8%ac-%d9%8a%d8%aa%d8%ad%d8%af%d8%ab-%d8%b9%d9%86-%d8%b4%d8%ae%d8%b5%d9%8a%d8%aa%d9%87-%d9%88%d8%a7%d9%84%d8%a7%d8%b3%d8%aa%d9%81%d8%a7%d8%af%d8%a9-%d9%85%d9%86-%d8%a7%d9%84%d9%85%d9%86%d8%a7%d9%81%d8%b3%d9%8a%d9%86-%d9%88%d8%a5%d8%af%d8%a7%d8%b1%d8%a9-%d8%a7%d9%84%d9%84%d8%a7%d8%b9%d8%a8%d9%8a%d9%86",
    "summary": "ارتبط اسم المدرب الدنماركي توماس توماسبيرج، بتولي منصب المدير الفني الجديد للنادي الأهلي، بعد دخول الفريق الأحمر في مفاوضات متقدمة معه.",
    "body": null,
    "image": null,
    "pubDate": "2025-09-28T13:25:00.000Z",
    "source": {
      "name": "Yallakora",
      "homepage": "https://www.yallakora.com/feed/rssfeed"
    },
    "lang": "en",
    "category": "entertainment",
    "region": "global"
  },
  {
    "id": "014aa631c01d8296",
    "title": "الراتب وموعد الوصول.. مصدر ليلا كورة: الأهلي يتوصل لإتفاق مع توماسبيرج حتى 2027",
    "link": "https://www.yallakora.com/egyptian-league/2977/news/524981/%d8%a7%d9%84%d8%b1%d8%a7%d8%aa%d8%a8-%d9%88%d9%85%d9%88%d8%b9%d8%af-%d8%a7%d9%84%d9%88%d8%b5%d9%88%d9%84-%d9%85%d8%b5%d8%af%d8%b1-%d9%84%d9%8a%d9%84%d8%a7-%d9%83%d9%88%d8%b1%d8%a9-%d8%a7%d9%84%d8%a3%d9%87%d9%84%d9%8a-%d9%8a%d8%aa%d9%88%d8%b5%d9%84-%d9%84%d8%a5%d8%aa%d9%81%d8%a7%d9%82-%d9%85%d8%b9-%d8%aa%d9%88%d9%85%d8%a7%d8%b3%d8%a8%d9%8a%d8%b1%d8%ac-%d8%ad%d8%aa%d9%89-2027",
    "summary": "توصل النادي الأهلي لاتفاق نهائي مع الدنماركي توماس توماسبرج المدير الفني السابق لميتييلاند الدنماركي، لتولي منصب مدرب الفريق.",
    "body": null,
    "image": null,
    "pubDate": "2025-09-28T12:24:00.000Z",
    "source": {
      "name": "Yallakora",
      "homepage": "https://www.yallakora.com/feed/rssfeed"
    },
    "lang": "en",
    "category": "entertainment",
    "region": "global"
  },
  {
    "id": "24e59b16fa1c7257",
    "title": "مصدر ليلا كورة: الأهلي في مفاوضات متقدمة مع توماسبيرج.. والحسم بعد القمة",
    "link": "https://www.yallakora.com/egyptian-league/2977/news/524970/%d9%85%d8%b5%d8%af%d8%b1-%d9%84%d9%8a%d9%84%d8%a7-%d9%83%d9%88%d8%b1%d8%a9-%d8%a7%d9%84%d8%a3%d9%87%d9%84%d9%8a-%d9%81%d9%8a-%d9%85%d9%81%d8%a7%d9%88%d8%b6%d8%a7%d8%aa-%d9%85%d8%aa%d9%82%d8%af%d9%85%d8%a9-%d9%85%d8%b9-%d8%aa%d9%88%d9%85%d8%a7%d8%b3%d8%a8%d9%8a%d8%b1%d8%ac-%d9%88%d8%a7%d9%84%d8%ad%d8%b3%d9%85-%d8%a8%d8%b9%d8%af-%d8%a7%d9%84%d9%82%d9%85%d8%a9",
    "summary": "وصل النادي الأهلي إلى مفاوضات متقدمة مع الدنماركي توماس توماسبرج المدير الفني السابق لميتييلاند الدنماركي، لتولي منصب مدرب الفريق.",
    "body": null,
    "image": null,
    "pubDate": "2025-09-28T10:28:00.000Z",
    "source": {
      "name": "Yallakora",
      "homepage": "https://www.yallakora.com/feed/rssfeed"
    },
    "lang": "en",
    "category": "entertainment",
    "region": "global"
  }
]