[
  {
    "id": "45f13d76ebcabbd9",
    "title": "Alienware 16 Area-51 review: OLED screen update",
    "link": "https://www.tomshardware.com/laptops/gaming-laptops/alienware-16-area-51-oled-2026-review",
    "summary": "The Alienware 16 Area-51 is a slightly updated spaceship of a laptop that's powerful and finally gets an OLED display option.",
    "body": null,
    "image": "https://cdn.mos.cms.futurecdn.net/i2HPk7nEgQGeJGbur5ehQB-1280-80.jpg",
    "pubDate": "2026-05-04T16:54:39.000Z",
    "source": {
      "name": "Tom's Hardware",
      "homepage": "https://www.tomshardware.com/feeds/all"
    },
    "lang": "en",
    "category": "science",
    "region": "global"
  }
]