[
  {
    "id": "9bb0d8568e55ca51",
    "title": "Samsung SmartThings gets Now Brief integration",
    "link": "https://www.gsmarena.com/samsung_smartthings_gets_now_brief_integration-news-72399.php",
    "summary": "Samsung announced that its SmartThings home automation system now supports Now Brief integration. Now Brief made its debut on the Galaxy S25 series and provides glanceable contextual information like weather updates, upcoming calendar events and reminders on supported Galaxy devices. With the new u…",
    "body": null,
    "image": null,
    "pubDate": "2026-04-16T14:13:02.000Z",
    "source": {
      "name": "GSMArena",
      "homepage": "https://www.gsmarena.com/rss-news-reviews.php3"
    },
    "lang": "en",
    "category": "weather",
    "region": "global"
  }
]