[
  {
    "id": "615bd962348a5ae0",
    "title": "Woodside energy Q3 revenue falls 9%, co hikes 2025 production forecast",
    "link": "https://www.investing.com/news/stock-market-news/woodside-energy-q3-revenue-falls-9-co-hikes-2025-production-forecast-4300489",
    "summary": "",
    "body": null,
    "image": null,
    "pubDate": "2025-10-21T23:41:06.000Z",
    "source": {
      "name": "Investing.com News (EN)",
      "homepage": "https://www.investing.com/rss/news.rss"
    },
    "lang": "en",
    "category": "weather",
    "region": "global"
  }
]